lethe/LICENSE.md
lethe/README.md
lethe/__init__.py
lethe/__main__.py
lethe/endpoints.py
lethe/lethe.py
lethe/py.typed
lethe-0.13.dist-info/METADATA
lethe-0.13.dist-info/WHEEL
lethe-0.13.dist-info/entry_points.txt
lethe-0.13.dist-info/licenses/LICENSE.md
lethe-0.13.dist-info/RECORD
