Metadata-Version: 2.1
Name: lethe
Version: 0.13
Summary: Lithography mask library
Author-email: Jan Petykiewicz <jan@mpxd.net>
License: GNU General Public License
Keywords: backup,commit,git,lab notebook,log,refs,snapshot,traceability,undo
Classifier: Development Status :: 4 - Beta
Classifier: Environment :: Other Environment
Classifier: Intended Audience :: Developers
Classifier: Intended Audience :: Science/Research
Classifier: License :: OSI Approved :: GNU General Public License v3 (GPLv3)
Classifier: Programming Language :: Python :: 3
Classifier: Topic :: Software Development :: Version Control :: Git
Classifier: Topic :: Utilities
Requires-Python: >=3.8
